.gitignore
AUTHORS.txt
CHANGELOG.md
CONTRIBUTING.md
LICENSE.txt
README.md
setup.cfg
setup.py
.github/ISSUE_TEMPLATE/bug_report.md
.github/ISSUE_TEMPLATE/feature_request.md
.github/workflows/pythonapp.yml
doc/Makefile
doc/make.bat
doc/source/api.rst
doc/source/conf.py
doc/source/examples.rst
doc/source/flower.rst
doc/source/getting_started.rst
doc/source/index.rst
doc/source/installation.rst
kivy_garden.ebs.forms.egg-info/PKG-INFO
kivy_garden.ebs.forms.egg-info/SOURCES.txt
kivy_garden.ebs.forms.egg-info/dependency_links.txt
kivy_garden.ebs.forms.egg-info/requires.txt
kivy_garden.ebs.forms.egg-info/top_level.txt
kivy_garden/ebs/__init__.py
kivy_garden/ebs/forms/__init__.py
kivy_garden/ebs/forms/checkbox.py
kivy_garden/ebs/forms/spinner.py
kivy_garden/ebs/forms/switch.py
kivy_garden/ebs/forms/textbox.py
tools/hooks/pre-commit