Metadata-Version: 2.1
Name: kivy_garden.ebs.forms
Version: 1.1.1
Summary: Reusable form widgets
Home-page: https://github.com/ebs-universe/kivy_garden.ebs.forms
Author: Chintalagiri Shashank
Author-email: shashank.chintalagiri@gmail.com
Project-URL: Bug Reports, https://github.com/ebs-universe/kivy_garden.ebs.forms/issues
Project-URL: Source, https://github.com/ebs-universe/kivy_garden.ebs.forms
Keywords: Kivy kivy-garden
Classifier: Development Status :: 4 - Beta
Classifier: Intended Audience :: Developers
Classifier: Topic :: Software Development :: Libraries
Classifier: License :: OSI Approved :: MIT License
Classifier: Programming Language :: Python :: 3.5
Classifier: Programming Language :: Python :: 3.6
Classifier: Programming Language :: Python :: 3.7
Classifier: Programming Language :: Python :: 3.8
Classifier: Programming Language :: Python :: 3.9
Classifier: Programming Language :: Python :: 3.10
License-File: LICENSE.txt
License-File: AUTHORS.txt
Requires-Dist: kivy>=1.11.1
Requires-Dist: kivy_garden.ebs.core>=1.3.5
Requires-Dist: colorthief
Provides-Extra: dev
Requires-Dist: pytest>=3.6; extra == "dev"
Requires-Dist: pytest-cov; extra == "dev"
Requires-Dist: pytest-asyncio; extra == "dev"
Requires-Dist: sphinx_rtd_theme; extra == "dev"
Provides-Extra: ci
Requires-Dist: coveralls; extra == "ci"
Requires-Dist: pycodestyle; extra == "ci"
Requires-Dist: pydocstyle; extra == "ci"
